logbuddy/__init__.py
logbuddy/logbuddy.py
logbuddy-0.0.1.7.dist-info/METADATA
logbuddy-0.0.1.7.dist-info/RECORD
logbuddy-0.0.1.7.dist-info/WHEEL
logbuddy-0.0.1.7.dist-info/top_level.txt
