Metadata-Version: 2.1
Name: logbuddy
Version: 0.0.1.7
Summary: Loghandler
Home-page: https://gitlab.com/buddyspencer/logbuddy.git
Author: buddyspencer
Author-email: buddyspencer@protonmail.com
License: MIT
Keywords: example
Platform: UNKNOWN
